{
  "ncd_zlib": {
    "pca": {
      "embedding": [
        [
          -0.1916903960784981,
          0.10532351803328256
        ],
        [
          -0.2844578076184379,
          -0.10623076183256716
        ],
        [
          -0.29829639320700874,
          -0.2962140495103502
        ],
        [
          -0.22155122361101737,
          -0.3893860317645384
        ],
        [
          -0.3520560534973267,
          -0.2815815550391379
        ],
        [
          -0.14650225486731056,
          0.1967669032085877
        ],
        [
          -0.0005727917014355432,
          0.2934108078699611
        ],
        [
          0.3612314928289709,
          -0.16577258567926437
        ],
        [
          0.38143526468522704,
          -0.16572056053214101
        ],
        [
          -0.2513154056496187,
          0.1189171792948146
        ],
        [
          0.4055941289756775,
          -0.1825642096238289
        ],
        [
          0.4030335902035607,
          -0.21898997236067833
        ],
        [
          -0.053459880328735596,
          0.347947421881471
        ],
        [
          0.2505123040607064,
          0.31895858262515886
        ],
        [
          -0.0019045741947532786,
          0.4251353134292302
        ]
      ],
      "info": {
        "method": "PCA",
        "explained_variance_ratio": [
          0.08216466222176658,
          0.07396266742701868
        ],
        "cumulative_variance": [
          0.08216466222176658,
          0.15612732964878526
        ],
        "total_variance_explained": 0.15612732964878526,
        "n_components": 2
      }
    },
    "tsne": {
      "error": "TSNE.__init__() got an unexpected keyword argument 'n_iter'"
    },
    "umap": {
      "method": "UMAP",
      "error": "UMAP not installed"
    }
  },
  "ncd_lzma": {
    "pca": {
      "embedding": [
        [
          0.3401173955472711,
          -0.2482780485903331
        ],
        [
          0.38446660763813095,
          0.014925545114877934
        ],
        [
          0.24525687544076483,
          0.334049979994045
        ],
        [
          0.08377100778560023,
          0.6118309418191294
        ],
        [
          0.21794704054191216,
          0.41548649059888654
        ],
        [
          0.29289112520021504,
          -0.3772293191889003
        ],
        [
          0.10391309141404832,
          -0.36532799586999565
        ],
        [
          -0.3972706669729439,
          -0.051820129054424825
        ],
        [
          -0.4096571954003282,
          0.022649269750004634
        ],
        [
          0.2393103927554237,
          0.03380147351010543
        ],
        [
          -0.4147174317759987,
          0.02222698774416277
        ],
        [
          -0.4309736484967274,
          0.008361457629221643
        ],
        [
          0.04152914350661361,
          -0.21741282001182588
        ],
        [
          -0.3121093436380781,
          -0.027555105645018306
        ],
        [
          0.015525606454096364,
          -0.17570872779993424
        ]
      ],
      "info": {
        "method": "PCA",
        "explained_variance_ratio": [
          0.09981755761821538,
          0.08199346500324098
        ],
        "cumulative_variance": [
          0.09981755761821538,
          0.18181102262145638
        ],
        "total_variance_explained": 0.18181102262145638,
        "n_components": 2
      }
    },
    "tsne": {
      "error": "TSNE.__init__() got an unexpected keyword argument 'n_iter'"
    },
    "umap": {
      "method": "UMAP",
      "error": "UMAP not installed"
    }
  },
  "categories": {
    "grep": "text_processing",
    "sed": "text_processing",
    "gzip": "compression",
    "bzip2": "compression",
    "xz": "compression",
    "find": "system",
    "tar": "archives",
    "bash": "shells",
    "python3": "interpreters",
    "curl": "networking",
    "git": "version_control",
    "vim": "editors",
    "nano": "editors",
    "gcc": "compilers",
    "objdump": "unknown"
  },
  "category_summary": {
    "category_distribution": {
      "text_processing": 2,
      "compression": 3,
      "system": 1,
      "archives": 1,
      "shells": 1,
      "interpreters": 1,
      "networking": 1,
      "version_control": 1,
      "editors": 2,
      "compilers": 1,
      "unknown": 1
    },
    "num_categories": 11,
    "largest_category": [
      "compression",
      3
    ],
    "single_binary_categories": 8
  }
}